smsdrop/__init__.py
smsdrop/client.py
smsdrop/constants.py
smsdrop/errors.py
smsdrop/logger.py
smsdrop/models.py
smsdrop/py.typed
smsdrop/storages.py
smsdrop/utils.py
smsdrop_python-1.0.0.dist-info/LICENSE
smsdrop_python-1.0.0.dist-info/WHEEL
smsdrop_python-1.0.0.dist-info/METADATA
smsdrop_python-1.0.0.dist-info/RECORD
