Metadata-Version: 2.1
Name: smsdrop-python
Version: 1.0.0
Summary: A python sdk for the smsdrop.net platform
Home-page: https://github.com/Tobi-De/smsdrop-python
License: MIT
Keywords: Sdk,Sms,Api,Smsdrop,Campaign
Author: Tobi DEGNON
Author-email: tobidegnon@protonmail.com
Requires-Python: >=3.8,<4.0
Classifier: Development Status :: 5 - Production/Stable
Classifier: Intended Audience :: Developers
Classifier: License :: OSI Approved :: MIT License
Classifier: Natural Language :: English
Classifier: Programming Language :: Python :: 3
Classifier: Programming Language :: Python :: 3.10
Classifier: Programming Language :: Python :: 3.8
Classifier: Programming Language :: Python :: 3.9
Provides-Extra: redis
Requires-Dist: httpx (>=0.22.0,<0.23.0)
Requires-Dist: mkdocs (>=1.3.0,<2.0.0)
Requires-Dist: mkdocs-include-markdown-plugin (>=3.3.0,<4.0.0)
Requires-Dist: mkdocs-material (>=8.2.9,<9.0.0)
Requires-Dist: mkdocs-material-extensions (>=1.0.3,<2.0.0)
Requires-Dist: mkdocstrings (>=0.18.1,<0.19.0)
Requires-Dist: redis (==4.2.2); extra == "redis"
Requires-Dist: tenacity (>=8.0.1,<9.0.0)
Project-URL: Repository, https://github.com/Tobi-De/smsdrop-python
